setup.cfg
setup.py
seaborn_timestamp/__init__.py
seaborn_timestamp/time_profile.py
seaborn_timestamp/timestamp.py
seaborn_timestamp.egg-info/PKG-INFO
seaborn_timestamp.egg-info/SOURCES.txt
seaborn_timestamp.egg-info/dependency_links.txt
seaborn_timestamp.egg-info/requires.txt
seaborn_timestamp.egg-info/top_level.txt
test/test_time_profile.py
test/test_timestamp.py