Metadata-Version: 1.1
Name: seaborn-timestamp
Version: 1.1.0
Summary: Seaborn Timestamp has timing functions and a timing profile which collects and reports on timing data of code execution
Home-page: https://github.com/SeabornGames/Timestamp
Author: Ben Christenson
Author-email: Python@BenChristenson.com
License: MIT License
Platform: UNKNOWN
Classifier: Intended Audience :: Developers
Classifier: Natural Language :: English
Classifier: License :: Other/Proprietary License
Classifier: Operating System :: POSIX :: Linux
Classifier: Programming Language :: Python
Classifier: Programming Language :: Python :: 2.7
Classifier: Programming Language :: Python :: 3.5
